clang/__init__.py
clang/clang.py
robotframework_clang-0.1.0.dist-info/licenses/LICENSE
robotframework_clang-0.1.0.dist-info/licenses/LICENSE.md
robotframework_clang-0.1.0.dist-info/METADATA
robotframework_clang-0.1.0.dist-info/WHEEL
robotframework_clang-0.1.0.dist-info/top_level.txt
robotframework_clang-0.1.0.dist-info/RECORD
