Metadata-Version: 2.4
Name: robotframework-clang
Version: 0.1.0
Summary: Robot Framework library for Clang-REPL execution via xeus-cpp
Author: Massimo Rossello
License: Apache-2.0
Classifier: Framework :: Robot Framework
Classifier: Programming Language :: Python :: 3
Classifier: License :: OSI Approved :: Apache Software License
Requires-Python: >=3.8
License-File: LICENSE
License-File: LICENSE.md
Requires-Dist: robotframework
Requires-Dist: jupyter_client
Requires-Dist: docutils
Provides-Extra: docs
Requires-Dist: sphinx; extra == "docs"
Requires-Dist: sphinx_rtd_theme; extra == "docs"
Requires-Dist: myst-parser; extra == "docs"
Dynamic: license-file
